rakam/__init__.py
rakam/client.py
rakam/connection.py
rakam/exceptions.py
rakam/sql.py
rakam/utils.py
rakam-0.1.3.dist-info/DESCRIPTION.rst
rakam-0.1.3.dist-info/METADATA
rakam-0.1.3.dist-info/RECORD
rakam-0.1.3.dist-info/WHEEL
rakam-0.1.3.dist-info/metadata.json
rakam-0.1.3.dist-info/top_level.txt
