Metadata-Version: 2.0
Name: rakam
Version: 0.1.3
Summary: Python client for rakam server.
Home-page: https://github.com/kakashit/rakam_client
Author: Kaan Uğurlu
Author-email: kugurlu94@gmail.com
License: UNKNOWN
Platform: any
Classifier: Development Status :: 2 - Pre-Alpha
Classifier: Environment :: Web Environment
Classifier: Intended Audience :: Developers
Classifier: Operating System :: OS Independent
Classifier: Programming Language :: Python
Classifier: Programming Language :: Python :: 2
Classifier: Programming Language :: Python :: 2.7
Classifier: Programming Language :: Python :: 3
Classifier: Programming Language :: Python :: 3.3
Requires-Dist: pytz (>=2016.4)
Requires-Dist: requests (>=2.4.3)
Requires-Dist: six (>=1.10.0)
